src/__init__.py
src/__version__.py
src/main.py
my_hw-0.1.56.dist-info/METADATA
my_hw-0.1.56.dist-info/WHEEL
my_hw-0.1.56.dist-info/entry_points.txt
my_hw-0.1.56.dist-info/licenses/LICENSE
my_hw-0.1.56.dist-info/RECORD
